autogen_google_search/__init__.py
autogen_google_search/google_search.py
autogen_google_search-0.0.5.dist-info/LICENSE
autogen_google_search-0.0.5.dist-info/METADATA
autogen_google_search-0.0.5.dist-info/WHEEL
autogen_google_search-0.0.5.dist-info/top_level.txt
autogen_google_search-0.0.5.dist-info/RECORD
