Metadata-Version: 2.1
Name: autogen_google_search
Version: 0.0.5
Summary: A tool that integrates the autogen with Google Searcher.
Author-email: auserwn <auserwn@yeah.net>
Classifier: Programming Language :: Python :: 3
Classifier: License :: OSI Approved :: MIT License
Classifier: Operating System :: OS Independent
Requires-Python: >=3.11
License-File: LICENSE
Requires-Dist: pyautogen >=0.2.14
Requires-Dist: requests >=2.31.0
Requires-Dist: langchain >=0.1.9
Requires-Dist: langchain-community >=0.0.24
Requires-Dist: langchain-openai >=0.0.8
Requires-Dist: langchain-core >=0.1.27
